LICENSE.txt
MANIFEST.in
README.md
setup.py
django_withings.egg-info/PKG-INFO
django_withings.egg-info/SOURCES.txt
django_withings.egg-info/dependency_links.txt
django_withings.egg-info/requires.txt
django_withings.egg-info/top_level.txt
requirements/base.txt
requirements/dev.txt
requirements/test.txt
withingsapp/__init__.py
withingsapp/decorators.py
withingsapp/defaults.py
withingsapp/models.py
withingsapp/urls.py
withingsapp/utils.py
withingsapp/views.py
withingsapp/migrations/0001_initial.py
withingsapp/migrations/0002_help_text.py
withingsapp/migrations/__init__.py
withingsapp/templates/withings/error.html
withingsapp/templatetags/__init__.py
withingsapp/templatetags/withings.py
withingsapp/tests/__init__.py
withingsapp/tests/base.py
withingsapp/tests/test_integration.py
withingsapp/tests/test_models.py
withingsapp/tests/test_retrieval.py
withingsapp/tests/test_utils.py